tikzify/__init__.py
tikzify/py.typed
tikzify/_src/__init__.py
tikzify/_src/foundation/__init__.py
tikzify/_src/foundation/context.py
tikzify/_src/foundation/elements.py
tikzify/_src/foundation/function.py
tikzify/_src/function_graph/__init__.py
tikzify/_src/function_graph/annotation.py
tikzify/_src/function_graph/curve_generator.py
tikzify/_src/function_graph/draw.py
tikzify/_src/function_graph/graph.py
tikzify/_src/function_graph/legend.py
tikzify/_src/function_graph/multi_graph.py
tikzify/_src/function_graph/trait.py
tikzify/_src/function_graph/curve_source/__init__.py
tikzify/_src/function_graph/curve_source/curve_source.py
tikzify/_src/function_graph/curve_source/function.py
tikzify/_src/function_graph/curve_source/trajectory.py
tikzify/_src/node_graph/__init__.py
tikzify/_src/node_graph/anchor.py
tikzify/_src/node_graph/constraints.py
tikzify/_src/node_graph/edge.py
tikzify/_src/node_graph/graph.py
tikzify/_src/node_graph/multi_edge.py
tikzify/_src/node_graph/node.py
tikzify/_src/node_graph/tips.py
tikzify/_src/node_graph/tools.py
tikzify-2.0.0.dist-info/METADATA
tikzify-2.0.0.dist-info/WHEEL
tikzify-2.0.0.dist-info/licenses/LICENSE
tikzify-2.0.0.dist-info/RECORD
