Metadata-Version: 2.4
Name: tikzify
Version: 2.0.0
Summary: Utilities for programmatically generating TikZ code.
Project-URL: source, https://github.com/NeilGirdhar/tikzify
Author: Neil Girdhar
Author-email: mistersheik@gmail.com
Maintainer: Neil Girdhar
Maintainer-email: mistersheik@gmail.com
License-Expression: Apache-2.0
License-File: LICENSE
Classifier: Development Status :: 4 - Beta
Classifier: Intended Audience :: Developers
Classifier: License :: OSI Approved :: Apache Software License
Classifier: Operating System :: OS Independent
Classifier: Programming Language :: Python
Classifier: Programming Language :: Python :: 3
Classifier: Programming Language :: Python :: 3.11
Classifier: Programming Language :: Python :: 3.12
Classifier: Programming Language :: Python :: 3.13
Classifier: Topic :: Scientific/Engineering :: Visualization
Classifier: Topic :: Software Development :: Libraries :: Python Modules
Classifier: Topic :: Utilities
Classifier: Typing :: Typed
Requires-Python: <3.14,>=3.11
Requires-Dist: more-itertools>=10
Requires-Dist: networkx>=3.1
Requires-Dist: numpy>=1.25
Requires-Dist: rectangle>=0.5.1
Requires-Dist: scipy-stubs>=1.15
Requires-Dist: scipy>=1.11
